univoc/__init__.py
univoc/dataset.py
univoc/model.py
univoc/config/config.yaml
univoc/config/preprocess.yaml
univoc/config/train.yaml
univoc-0.2.1.dist-info/LICENSE
univoc-0.2.1.dist-info/METADATA
univoc-0.2.1.dist-info/WHEEL
univoc-0.2.1.dist-info/top_level.txt
univoc-0.2.1.dist-info/RECORD
