Metadata-Version: 2.1
Name: univoc
Version: 0.2.1
Summary: A PyTorch implementation of Towards Achieving Robust Universal Neural Vocoding.
Home-page: https://github.com/bshall/UniversalVocoding
Author: Benjamin van Niekerk
Author-email: benjamin.l.van.niekerk@gmail.com
License: UNKNOWN
Project-URL: Source, https://github.com/bshall/UniversalVocoding
Project-URL: Samples, https://bshall.github.io/UniversalVocoding/
Keywords: Speech Synthesis,Neural Vocoder,Text-to-Speech,PyTorch
Platform: UNKNOWN
Classifier: Natural Language :: English
Classifier: Intended Audience :: Science/Research
Classifier: License :: OSI Approved :: MIT License
Classifier: Operating System :: POSIX :: Linux
Classifier: Programming Language :: Python
Classifier: Programming Language :: Python :: 3.6
Classifier: Programming Language :: Python :: 3.7
Classifier: Programming Language :: Python :: 3.8
Classifier: Programming Language :: Python :: 3.9
Classifier: Topic :: Scientific/Engineering
Classifier: Topic :: Scientific/Engineering :: Artificial Intelligence
Requires-Python: >=3.6
Requires-Dist: librosa (>=0.8.0)
Requires-Dist: numpy (>=1.18.0)
Requires-Dist: tqdm (>=4.41)
Requires-Dist: requests
Requires-Dist: importlib-resources
Requires-Dist: omegaconf (>=2.0.3)
